yamt/__init__.py
yamt/asyncio_misc.py
yamt/asyncio_sync_primitives.py
yamt/collections.py
yamt/decoration_trigger.py
yamt/enum.py
yamt/exceptions.py
yamt/misc.py
yamt/typing.py
yamt-1.0.2.dist-info/LICENSE
yamt-1.0.2.dist-info/WHEEL
yamt-1.0.2.dist-info/METADATA
yamt-1.0.2.dist-info/RECORD
