Metadata-Version: 2.1
Name: yamt
Version: 1.0.2
Summary: yet another monkey toolkit
License: MIT
Keywords: utils,tools,misc
Author: lightmanLP
Author-email: liteman1000@gmail.com
Requires-Python: >=3.10,<4.0
Classifier: License :: OSI Approved :: MIT License
Classifier: Programming Language :: Python :: 3
Classifier: Programming Language :: Python :: 3.10
Classifier: Programming Language :: Python :: 3.11
Project-URL: Github, https://github.com/UT1C/yamt
